robolearn/__init__.py
robolearn-0.0.0.dist-info/DESCRIPTION.rst
robolearn-0.0.0.dist-info/METADATA
robolearn-0.0.0.dist-info/RECORD
robolearn-0.0.0.dist-info/WHEEL
robolearn-0.0.0.dist-info/metadata.json
robolearn-0.0.0.dist-info/top_level.txt
